.gitignore
MANIFEST.in
README.txt
setup.py
XStatic_JQuery.Bootstrap.Wizard.egg-info/PKG-INFO
XStatic_JQuery.Bootstrap.Wizard.egg-info/SOURCES.txt
XStatic_JQuery.Bootstrap.Wizard.egg-info/dependency_links.txt
XStatic_JQuery.Bootstrap.Wizard.egg-info/namespace_packages.txt
XStatic_JQuery.Bootstrap.Wizard.egg-info/not-zip-safe
XStatic_JQuery.Bootstrap.Wizard.egg-info/top_level.txt
xstatic/__init__.py
xstatic/pkg/__init__.py
xstatic/pkg/jquery_bootstrap_wizard/__init__.py
xstatic/pkg/jquery_bootstrap_wizard/data/jquery.bootstrap.wizard.js