Metadata-Version: 1.0
Name: XStatic-JQuery.Bootstrap.Wizard
Version: 1.0.0.1
Summary: JQuery.Bootstrap.Wizard 1.0.0 (XStatic packaging standard)
Home-page: http://github.com/VinceG/twitter-bootstrap-wizard
Author: Radomir Dopieralski
Author-email: openstack@sheep.art.pl
License: (same as JQuery.Bootstrap.Wizard)
Keywords: jquery_bootstrap_wizard xstatic
Platform: any
